wad2023_program/__init__.py
wad2023_program/__main__.py
wad2023_program/app_config.py
wad2023_program/database.py
wad2023_program/exceptions.py
wad2023_program/model.py
wad2023_program/sessionize_parser.py
wad2023_program/sync.py
wad2023_program/view.py
wad2023_program-1.3.0.dist-info/LICENSE
wad2023_program-1.3.0.dist-info/METADATA
wad2023_program-1.3.0.dist-info/WHEEL
wad2023_program-1.3.0.dist-info/entry_points.txt
wad2023_program-1.3.0.dist-info/top_level.txt
wad2023_program-1.3.0.dist-info/RECORD
