Metadata-Version: 2.1
Name: wad2023-program
Version: 1.3.0
Summary: Script to retrieve the program for WeAreDevelopers 2023 conference
Author-email: Daryl Stark <daryl@dstark.nl>
License: MIT License
Project-URL: homepage, https://github.com/DarylStark/WeAreDevelopers_2023_Program
Project-URL: repository, https://github.com/DarylStark/WeAreDevelopers_2023_Program
Keywords: conference,program,wearedevelopers,wearedevs
Classifier: Programming Language :: Python
Classifier: Programming Language :: Python :: 3
Requires-Python: >=3.10
License-File: LICENSE
Requires-Dist: requests (>=2.27.0)
Requires-Dist: pydantic (>=1.10.0)
Requires-Dist: beautifulsoup4 (>=4.12.0)
Requires-Dist: python-dateutil (>=2.8.0)
Requires-Dist: rich (>=13.4.0)
Requires-Dist: typer (>=0.9.0)
Requires-Dist: pytz (>=2023.3)
Requires-Dist: sqlmodel (==0.0.8)
Provides-Extra: dev
Requires-Dist: pytest (>=7.3.0) ; extra == 'dev'
Requires-Dist: pycodestyle (==2.10.0) ; extra == 'dev'
Requires-Dist: autopep8 (==2.0.0) ; extra == 'dev'
Requires-Dist: pylint (==2.17.0) ; extra == 'dev'
Requires-Dist: mypy (==1.3.0) ; extra == 'dev'
Requires-Dist: flake8 (==6.0.0) ; extra == 'dev'
Requires-Dist: pydocstyle (==6.3.0) ; extra == 'dev'
Requires-Dist: pg8000 (>=1.29.0) ; extra == 'dev'
